dbtf/__about__.py
dbtf/__init__.py
dbtf/__main__.py
dbtf/factory.py
dbtf/cli/__init__.py
dbtf/dbt_project/dbt_project.yml
dbtf/dbt_project/factory_config.yml
dbtf/dbt_project/profiles.yml
dbtf/dbt_project/models/.gitignore
dbtf/dbt_project/models/.gitkeep
dbtf/dbt_project/models/0.test_append.sql
dbtf/dbt_project/seeds/test_table_1.csv
dbtf/dbt_project/seeds/test_table_2.csv
dbtf/dbt_project/templates/append.sql
dbtf-0.0.14.dist-info/METADATA
dbtf-0.0.14.dist-info/WHEEL
dbtf-0.0.14.dist-info/entry_points.txt
dbtf-0.0.14.dist-info/licenses/LICENSE.txt
dbtf-0.0.14.dist-info/RECORD
