Metadata-Version: 2.1
Name: dbtf
Version: 0.0.14
Project-URL: Documentation, https://github.com/unknown/dbtf#readme
Project-URL: Issues, https://github.com/unknown/dbtf/issues
Project-URL: Source, https://github.com/unknown/dbtf
Author-email: "U.N. Owen" <void@some.where>
License-Expression: MIT
License-File: LICENSE.txt
Classifier: Development Status :: 4 - Beta
Classifier: Programming Language :: Python
Classifier: Programming Language :: Python :: 3.7
Classifier: Programming Language :: Python :: 3.8
Classifier: Programming Language :: Python :: 3.9
Classifier: Programming Language :: Python :: 3.10
Classifier: Programming Language :: Python :: 3.11
Classifier: Programming Language :: Python :: Implementation :: CPython
Classifier: Programming Language :: Python :: Implementation :: PyPy
Requires-Python: >=3.7
Requires-Dist: click
Requires-Dist: pyyaml==6.0.0
